levdict/__init__.py
levdict/levdict_base.py
levdict/levdict_json.py
levdict/levdict_toml.py
levdict/levdict_yaml.py
levdict-2023.4.dist-info/LICENSE
levdict-2023.4.dist-info/METADATA
levdict-2023.4.dist-info/WHEEL
levdict-2023.4.dist-info/top_level.txt
levdict-2023.4.dist-info/RECORD
