Metadata-Version: 2.1
Name: levdict
Version: 2023.4
Summary: Allows to manage dictionaries and config files as class attributes
Author-email: Fernando Levin <flevin58@gmail.com>
License: The MIT License (MIT)
Project-URL: Source, https://github.com/flevin58/levdict
Project-URL: Documentation, https://github.com/flevin58/levdict
Classifier: Programming Language :: Python :: 3
Classifier: License :: OSI Approved :: MIT License
Classifier: Operating System :: OS Independent
Requires-Python: >=3.8
License-File: LICENSE
Requires-Dist: toml
Requires-Dist: pyyaml
